xleapp/__init__.py
xleapp/__main__.py
xleapp/_authors.py
xleapp/_version.py
xleapp/app.py
xleapp/artifacts/__init__.py
xleapp/artifacts/abstract.py
xleapp/artifacts/decorators.py
xleapp/artifacts/descriptors.py
xleapp/artifacts/services.py
xleapp/artifacts/services.pyi
xleapp/globals.py
xleapp/gui/__init__.py
xleapp/gui/layout.py
xleapp/gui/log.py
xleapp/gui/utils.py
xleapp/helpers/__init__.py
xleapp/helpers/db.py
xleapp/helpers/decorators.py
xleapp/helpers/descriptors.py
xleapp/helpers/image.py
xleapp/helpers/search.py
xleapp/helpers/strings.py
xleapp/helpers/types.py
xleapp/helpers/utils.py
xleapp/log/__init__.py
xleapp/log/log_config.yaml
xleapp/plugins.py
xleapp/py.typed
xleapp/report/__init__.py
xleapp/report/_static/chats.css
xleapp/report/_static/dark-mode-switch.js
xleapp/report/_static/dark-mode.css
xleapp/report/_static/dashboard.css
xleapp/report/_static/feather.min.js
xleapp/report/_static/logo.jpg
xleapp/report/_static/MDB-Free_4.13.0/css/addons/datatables-select.min.css
xleapp/report/_static/MDB-Free_4.13.0/css/addons/datatables.min.css
xleapp/report/_static/MDB-Free_4.13.0/css/addons/directives.min.css
xleapp/report/_static/MDB-Free_4.13.0/css/addons/flag.min.css
xleapp/report/_static/MDB-Free_4.13.0/css/addons/jquery.zmd.hierarchical-display.min.css
xleapp/report/_static/MDB-Free_4.13.0/css/addons/rating.min.css
xleapp/report/_static/MDB-Free_4.13.0/css/bootstrap.css
xleapp/report/_static/MDB-Free_4.13.0/css/bootstrap.min.css
xleapp/report/_static/MDB-Free_4.13.0/css/mdb.css
xleapp/report/_static/MDB-Free_4.13.0/css/mdb.lite.css
xleapp/report/_static/MDB-Free_4.13.0/css/mdb.min.css
xleapp/report/_static/MDB-Free_4.13.0/img/overlays/01.png
xleapp/report/_static/MDB-Free_4.13.0/img/overlays/02.png
xleapp/report/_static/MDB-Free_4.13.0/img/overlays/03.png
xleapp/report/_static/MDB-Free_4.13.0/img/overlays/04.png
xleapp/report/_static/MDB-Free_4.13.0/img/overlays/05.png
xleapp/report/_static/MDB-Free_4.13.0/img/overlays/06.png
xleapp-0.2.1.dist-info/entry_points.txt
xleapp-0.2.1.dist-info/LICENSE
xleapp-0.2.1.dist-info/WHEEL
xleapp-0.2.1.dist-info/METADATA
xleapp-0.2.1.dist-info/RECORD
