Metadata-Version: 2.1
Name: xleapp
Version: 0.2.1
Summary: Multiplaform Logs, Events, And Plists Parser
Home-page: https://github.com/flamusdiu/xleapp
License: MIT
Keywords: forensics,dfir,security,framework
Author: Jesse Spangenberger
Author-email: azuleonyx@digitalforensics.io
Requires-Python: >=3.9,<4.0
Classifier: Development Status :: 3 - Alpha
Classifier: License :: OSI Approved :: MIT License
Classifier: Programming Language :: Python
Classifier: Programming Language :: Python :: 3
Classifier: Programming Language :: Python :: 3.10
Classifier: Programming Language :: Python :: 3.9
Classifier: Topic :: Security
Classifier: Topic :: Utilities
Classifier: Typing :: Typed
Requires-Dist: Jinja2 (>=3.0.2,<4.0.0)
Requires-Dist: PySimpleGUI (>=4.53.0,<5.0.0)
Requires-Dist: PyYAML (>=6.0,<7.0)
Requires-Dist: prettytable (>=2.2.1,<3.0.0)
Requires-Dist: python-magic-bin (>=0.4.14,<0.5.0)
Requires-Dist: simplekml (>=1.3.6,<2.0.0)
Requires-Dist: wrapt (>=1.13.2,<2.0.0)
Project-URL: Documentation, https://github.com/flamusdiu/xleapp
Project-URL: Repository, https://github.com/flamusdiu/xleapp
